human_readable_id/__init__.py
human_readable_id/api.py
human_readable_id/cli.py
human_readable_id/words/objects.txt
human_readable_id/words/predicates.txt
human_readable_id-0.0.3.dist-info/licenses/LICENSE
human_readable_id-0.0.3.dist-info/METADATA
human_readable_id-0.0.3.dist-info/WHEEL
human_readable_id-0.0.3.dist-info/entry_points.txt
human_readable_id-0.0.3.dist-info/top_level.txt
human_readable_id-0.0.3.dist-info/RECORD
