Metadata-Version: 2.4
Name: human-readable-id
Version: 0.0.3
Summary: Human Readable ID (hrid) generates short, human-readable, collision-aware, friendly IDs that are ideal for experiments, jobs, and filenames.
Author-email: Karol Gotkowski <KarolGotkowski@gmx.de>
License: MIT
Project-URL: Homepage, https://github.com/Karol-G/human-readable-id
Project-URL: Source, https://github.com/Karol-G/human-readable-id
Project-URL: Issues, https://github.com/Karol-G/human-readable-id/issues
Keywords: copier,template,python
Classifier: Programming Language :: Python
Classifier: Programming Language :: Python :: 3
Classifier: Programming Language :: Python :: 3 :: Only
Classifier: Programming Language :: Python :: 3.9
Classifier: Programming Language :: Python :: 3.10
Classifier: Programming Language :: Python :: 3.11
Classifier: Programming Language :: Python :: 3.12
Classifier: Programming Language :: Python :: 3.13
Classifier: Operating System :: OS Independent
Requires-Python: >=3.9
License-File: LICENSE
Provides-Extra: dev
Requires-Dist: build>=1.0; extra == "dev"
Requires-Dist: pytest>=7.0; extra == "dev"
Requires-Dist: twine>=4.0; extra == "dev"
Requires-Dist: setuptools_scm[toml]>=8.0; extra == "dev"
Dynamic: license-file
